TEM_comms/__init__.py
TEM_comms/buffer.py
TEM_comms/calibration.py
TEM_comms/camera.py
TEM_comms/lens_correction.py
TEM_comms/montage.py
TEM_comms/qc.py
TEM_comms/roi.py
TEM_comms/state.py
TEM_comms/ui.py
TEM_comms/scope/__init__.py
TEM_comms/scope/image_shift.py
TEM_comms/stage/__init__.py
TEM_comms/stage/aperture.py
TEM_comms/stage/motion.py
TEM_comms/stage/rotation.py
TEM_comms/tile/__init__.py
TEM_comms/tile/metadata.py
TEM_comms/tile/statistics.py
pigeon_tem_comms-2.1.1.dist-info/licenses/LICENSE
pigeon_tem_comms-2.1.1.dist-info/METADATA
pigeon_tem_comms-2.1.1.dist-info/WHEEL
pigeon_tem_comms-2.1.1.dist-info/entry_points.txt
pigeon_tem_comms-2.1.1.dist-info/top_level.txt
pigeon_tem_comms-2.1.1.dist-info/RECORD
