Metadata-Version: 2.4
Name: pigeon-tem-comms
Version: 2.1.1
Summary: Pigeon messages for the next generation TEM imaging system.
Author-email: Cameron Devine <cameron.devine@alleninstitute.org>
License: BSD 3 Clause
Project-URL: Homepage, https://github.com/AllenInstitute/TEM_comms
Project-URL: Documentation, https://alleninstitute.github.io/TEM_architecture/topics.html
Project-URL: Repository, https://github.com/AllenInstitute/TEM_comms
Project-URL: Issues, https://github.com/AllenInstitute/TEM_comms/issues
Classifier: Intended Audience :: Developers
Classifier: License :: OSI Approved :: BSD License
Classifier: Programming Language :: Python :: 3.10
Classifier: Programming Language :: Python :: 3.11
Classifier: Programming Language :: Python :: 3.12
Requires-Python: >=3.10
License-File: LICENSE
Requires-Dist: pigeon-client
Requires-Dist: pydantic
Dynamic: license-file
